{
  "indexes": [
    {
      "collectionGroup": "messages",
      "queryScope": "COLLECTION",
      "fields": [
        { "fieldPath": "chatId",    "order": "ASCENDING" },
        { "fieldPath": "createdAt", "order": "ASCENDING" }
      ]
    },
    {
      "collectionGroup": "notifications",
      "queryScope": "COLLECTION",
      "fields": [
        { "fieldPath": "toUserId",  "order": "ASCENDING" },
        { "fieldPath": "createdAt", "order": "DESCENDING" }
      ]
    },
    {
      "collectionGroup": "interactions",
      "queryScope": "COLLECTION",
      "fields": [
        { "fieldPath": "otherUserId", "order": "ASCENDING" },
        { "fieldPath": "met",         "order": "ASCENDING" }
      ]
    }
  ],
  "fieldOverrides": []
}